LeProHQ/__init__.py
LeProHQ/adler_.py
LeProHQ/bfkl.py
LeProHQ/bmsn.py
LeProHQ/cg0.py
LeProHQ/cg0_.py
LeProHQ/cg1.py
LeProHQ/cg1_.py
LeProHQ/cgBar1.py
LeProHQ/cgBar1_.py
LeProHQ/color.py
LeProHQ/cq1.py
LeProHQ/cq1_.py
LeProHQ/cqBarF1.py
LeProHQ/cqBarF1_.py
LeProHQ/dq1.py
LeProHQ/dq1_.py
LeProHQ/nielsen.py
LeProHQ/partonic_vars.py
LeProHQ/utils.py
LeProHQ/version.py
LeProHQ/zeta.py
LeProHQ/data/cg1/cg1-F2_AA-bulk.dat
LeProHQ/data/cg1/cg1-F2_AA-thres.dat
LeProHQ/data/cg1/cg1-F2_VV-bulk.dat
LeProHQ/data/cg1/cg1-F2_VV-thres.dat
LeProHQ/data/cg1/cg1-FL_AA-bulk.dat
LeProHQ/data/cg1/cg1-FL_AA-thres.dat
LeProHQ/data/cg1/cg1-FL_VV-bulk.dat
LeProHQ/data/cg1/cg1-FL_VV-thres.dat
LeProHQ/data/cg1/cg1-x2g1_AA-bulk.dat
LeProHQ/data/cg1/cg1-x2g1_AA-thres.dat
LeProHQ/data/cg1/cg1-x2g1_VV-bulk.dat
LeProHQ/data/cg1/cg1-x2g1_VV-thres.dat
LeProHQ/data/cq1/cq1-F2_AA-bulk.dat
LeProHQ/data/cq1/cq1-F2_AA-thres.dat
LeProHQ/data/cq1/cq1-F2_VV-bulk.dat
LeProHQ/data/cq1/cq1-F2_VV-thres.dat
LeProHQ/data/cq1/cq1-FL_AA-bulk.dat
LeProHQ/data/cq1/cq1-FL_AA-thres.dat
LeProHQ/data/cq1/cq1-FL_VV-bulk.dat
LeProHQ/data/cq1/cq1-FL_VV-thres.dat
LeProHQ/data/cq1/cq1-x2g1_AA-bulk.dat
LeProHQ/data/cq1/cq1-x2g1_AA-thres.dat
LeProHQ/data/cq1/cq1-x2g1_VV-bulk.dat
LeProHQ/data/cq1/cq1-x2g1_VV-thres.dat
LeProHQ/raw/__init__.py
LeProHQ/raw/cg0.py
LeProHQ/raw/cg1_a10.py
LeProHQ/raw/cgBar1.py
LeProHQ/raw/cqBarF1.py
LeProHQ/raw/dq1.py
LeProHQ-0.2.5.dist-info/METADATA
LeProHQ-0.2.5.dist-info/WHEEL
LeProHQ-0.2.5.dist-info/top_level.txt
LeProHQ-0.2.5.dist-info/RECORD
