Metadata-Version: 2.1
Name: LeProHQ
Version: 0.2.5
Summary: (Un-)polarized Leptoproduction of Heavy Quarks
Home-page: https://github.com/felixhekhorn/LeProHQ
Author: F. Hekhorn
Author-email: felix.hekhorn@mi.infn.it
Classifier: Operating System :: Unix
Classifier: Programming Language :: Python
Classifier: Programming Language :: Python :: 3
Classifier: Topic :: Scientific/Engineering
Classifier: Topic :: Scientific/Engineering :: Physics
Requires-Python: >=3.7
Requires-Dist: numpy
Requires-Dist: numba
Requires-Dist: scipy
